odoo10_addon_mail_follower_custom_notification-10.0.1.0.1-py3.8-nspkg.pth
odoo/addons/mail_follower_custom_notification/README.rst
odoo/addons/mail_follower_custom_notification/__init__.py
odoo/addons/mail_follower_custom_notification/__manifest__.py
odoo/addons/mail_follower_custom_notification/controllers/__init__.py
odoo/addons/mail_follower_custom_notification/controllers/mail_controller.py
odoo/addons/mail_follower_custom_notification/i18n/am.po
odoo/addons/mail_follower_custom_notification/i18n/ar.po
odoo/addons/mail_follower_custom_notification/i18n/bg.po
odoo/addons/mail_follower_custom_notification/i18n/bs.po
odoo/addons/mail_follower_custom_notification/i18n/ca.po
odoo/addons/mail_follower_custom_notification/i18n/ca_ES.po
odoo/addons/mail_follower_custom_notification/i18n/cs.po
odoo/addons/mail_follower_custom_notification/i18n/da.po
odoo/addons/mail_follower_custom_notification/i18n/de.po
odoo/addons/mail_follower_custom_notification/i18n/el_GR.po
odoo/addons/mail_follower_custom_notification/i18n/en_AU.po
odoo/addons/mail_follower_custom_notification/i18n/en_GB.po
odoo/addons/mail_follower_custom_notification/i18n/es.po
odoo/addons/mail_follower_custom_notification/i18n/es_AR.po
odoo/addons/mail_follower_custom_notification/i18n/es_CL.po
odoo/addons/mail_follower_custom_notification/i18n/es_CO.po
odoo/addons/mail_follower_custom_notification/i18n/es_CR.po
odoo/addons/mail_follower_custom_notification/i18n/es_DO.po
odoo/addons/mail_follower_custom_notification/i18n/es_EC.po
odoo/addons/mail_follower_custom_notification/i18n/es_ES.po
odoo/addons/mail_follower_custom_notification/i18n/es_MX.po
odoo/addons/mail_follower_custom_notification/i18n/es_PE.po
odoo/addons/mail_follower_custom_notification/i18n/es_PY.po
odoo/addons/mail_follower_custom_notification/i18n/es_VE.po
odoo/addons/mail_follower_custom_notification/i18n/et.po
odoo/addons/mail_follower_custom_notification/i18n/fa.po
odoo/addons/mail_follower_custom_notification/i18n/fi.po
odoo10_addon_mail_follower_custom_notification-10.0.1.0.1.dist-info/METADATA
odoo10_addon_mail_follower_custom_notification-10.0.1.0.1.dist-info/WHEEL
odoo10_addon_mail_follower_custom_notification-10.0.1.0.1.dist-info/namespace_packages.txt
odoo10_addon_mail_follower_custom_notification-10.0.1.0.1.dist-info/top_level.txt
odoo10_addon_mail_follower_custom_notification-10.0.1.0.1.dist-info/RECORD
